randomjokeapi/__init__.py
randomjokeapi/api.py
randomjokeapi/base.py
randomjokeapi-0.0.1.dist-info/LICENSE
randomjokeapi-0.0.1.dist-info/METADATA
randomjokeapi-0.0.1.dist-info/WHEEL
randomjokeapi-0.0.1.dist-info/top_level.txt
randomjokeapi-0.0.1.dist-info/RECORD
