Metadata-Version: 2.1
Name: randomjokeapi
Version: 0.0.1
Summary: get current temperature from provider
Home-page: https://github.com/asrinvakili/RndomJokeAPI
Author: Asrin Vakili
Author-email: asrin_vakili@yahoo.com
Project-URL: Author, https://github.com/asrinvakili
Classifier: Programming Language :: Python :: 3
Classifier: License :: OSI Approved :: MIT License
Classifier: Operating System :: OS Independent
Requires-Python: >=3.6
License-File: LICENSE
Requires-Dist: requests
